sonarcloud_report/__init__.py
sonarcloud_report/__main__.py
sonarcloud_report/client.py
sonarcloud_report/generate_sonarcloud_project_report.py
sonarcloud_report/run.py
sonarcloud_report/templates/sonarcloud_report.j2
sonarcloud_report-0.1.0.dev4.dist-info/LICENCE
sonarcloud_report-0.1.0.dev4.dist-info/METADATA
sonarcloud_report-0.1.0.dev4.dist-info/WHEEL
sonarcloud_report-0.1.0.dev4.dist-info/entry_points.txt
sonarcloud_report-0.1.0.dev4.dist-info/top_level.txt
sonarcloud_report-0.1.0.dev4.dist-info/RECORD
