Metadata-Version: 2.1
Name: sonarcloud_report
Version: 0.1.0.dev4
Summary: Tool used to generate a report about the latest SonarCloud analysis of a project.
Author-email: "cedric.fdl-lupin" <cedric.fdl-ext@lupindental.com>
Maintainer-email: "cedric.fdl-lupin" <cedric.fdl-ext@lupindental.com>
Project-URL: Repository, https://gitlab.com/lupindental/arsene/devops/sonarcloud_report
Classifier: Programming Language :: Python :: 3.10
Classifier: Development Status :: 3 - Alpha
Requires-Python: >=3.10
License-File: LICENCE
Requires-Dist: jinja2
Requires-Dist: python-sonarqube-api
Requires-Dist: typer[all]
Provides-Extra: dev
Requires-Dist: coverage ; extra == 'dev'
Requires-Dist: pytest ; extra == 'dev'
